mollier/__init__.py
mollier-0.0.1.dist-info/LICENSE
mollier-0.0.1.dist-info/WHEEL
mollier-0.0.1.dist-info/METADATA
mollier-0.0.1.dist-info/RECORD
